cnfgen/__init__.py
cnfgen/graphs.py
cnfgen/info.py
cnfgen/localtypes.py
cnfgen/version.py
cnfgen/clihelpers/__init__.py
cnfgen/clihelpers/counting_helpers.py
cnfgen/clihelpers/cpls_helpers.py
cnfgen/clihelpers/dimacs_helpers.py
cnfgen/clihelpers/formula_helpers.py
cnfgen/clihelpers/graph_helpers.py
cnfgen/clihelpers/ordering_helpers.py
cnfgen/clihelpers/pebbling_helpers.py
cnfgen/clihelpers/php_helpers.py
cnfgen/clihelpers/pitfall_helpers.py
cnfgen/clihelpers/simple_helpers.py
cnfgen/clihelpers/transformation_helpers.py
cnfgen/clitools/__init__.py
cnfgen/clitools/cmdline.py
cnfgen/clitools/cnfgen.py
cnfgen/clitools/cnfshuffle.py
cnfgen/clitools/graph_args.py
cnfgen/clitools/graph_build.py
cnfgen/clitools/graph_docs.py
cnfgen/clitools/graph_fileinput.py
cnfgen/clitools/kthlist2pebbling.py
cnfgen/clitools/msg.py
cnfgen/clitools/pbgen.py
cnfgen/families/__init__.py
cnfgen/families/cliquecoloring.py
cnfgen/families/coloring.py
cnfgen/families/counting.py
cnfgen/families/cpls.py
cnfgen/families/dominatingset.py
cnfgen/families/graphisomorphism.py
cnfgen/families/ordering.py
cnfgen/families/pebbling.py
cnfgen/families/pigeonhole.py
cnfgen/families/pitfall.py
cnfgen/families/ramsey.py
cnfgen/families/randomformulas.py
cnfgen/families/randomkxor.py
cnfgen/families/subgraph.py
cnfgen/families/subsetcardinality.py
cnfgen/families/tseitin.py
cnfgen/formula/__init__.py
cnfgen/formula/basecnf.py
cnfgen/formula/baseopb.py
cnfgen/formula/cnf.py
cnfgen/formula/cnfio.py
cnfgen/formula/linear.py
cnfgen/formula/opb.py
cnfgen/formula/opbio.py
cnfgen/formula/variables.py
cnfgen/transformations/__init__.py
cnfgen/transformations/shuffle.py
cnfgen/transformations/substitutions.py
cnfgen/utils/__init__.py
cnfgen/utils/latexoutput.py
cnfgen/utils/opb.py
cnfgen/utils/parsedimacs.py
cnfgen/utils/solver.py
cnfgen-0.9.5.dist-info/licenses/LICENSE
cnfgen-0.9.5.dist-info/METADATA
cnfgen-0.9.5.dist-info/WHEEL
cnfgen-0.9.5.dist-info/entry_points.txt
cnfgen-0.9.5.dist-info/top_level.txt
cnfgen-0.9.5.dist-info/RECORD
