Metadata-Version: 2.4
Name: CNFgen
Version: 0.9.5
Summary: CNF formula generator
Author-email: Massimo Lauria <massimo.lauria@uniroma1.it>
License-Expression: GPL-3.0
Project-URL: Homepage, https://massimolauria.net/cnfgen
Project-URL: Repository, https://github.com/MassimoLauria/cnfgen
Project-URL: Documentation, https://cnfgen.readthedocs.io/en/latest/
Requires-Python: >=3.7
License-File: LICENSE
Requires-Dist: networkx>=2.4
Requires-Dist: pydot<4.0.0,>=1.2.3
Dynamic: license-file
